LICENSE
MANIFEST.in
setup.py
versiontools_support.py
taiga_contrib_mailjet_subscription/__init__.py
taiga_contrib_mailjet_subscription/apps.py
taiga_contrib_mailjet_subscription/services.py
taiga_contrib_mailjet_subscription/signal_handlers.py
taiga_contrib_mailjet_subscription/utils.py
taiga_contrib_mailjet_subscription.egg-info/PKG-INFO
taiga_contrib_mailjet_subscription.egg-info/SOURCES.txt
taiga_contrib_mailjet_subscription.egg-info/dependency_links.txt
taiga_contrib_mailjet_subscription.egg-info/requires.txt
taiga_contrib_mailjet_subscription.egg-info/top_level.txt