Metadata-Version: 1.1
Name: taiga-contrib-mailjet-subscription
Version: 3.0.1
Summary: Plugin to subscribe and unsubscribe users to the newsletter in Mailjet.
Home-page: https://github.com/taigaio/taiga-contrib-mailjet-subscription
Author: Taiga Agile LLC
Author-email: taiga@taiga.io
License: AGPL
Keywords: taiga,mailjet,integration
Platform: UNKNOWN
Classifier: Programming Language :: Python
Classifier: Development Status :: 4 - Beta
Classifier: Framework :: Django
Classifier: Intended Audience :: Developers
Classifier: License :: OSI Approved :: GNU Affero General Public License v3
Classifier: Operating System :: OS Independent
Classifier: Programming Language :: Python
Classifier: Topic :: Internet :: WWW/HTTP
